lexi_align/__init__.py
lexi_align/constants.py
lexi_align/core.py
lexi_align/metrics.py
lexi_align/models.py
lexi_align/py.typed
lexi_align/text_processing.py
lexi_align/visualize.py
lexi_align/adapters/__init__.py
lexi_align/adapters/base.py
lexi_align/adapters/litellm_adapter.py
lexi_align/adapters/llama_cpp_adapter.py
lexi_align/adapters/mixins.py
lexi_align/adapters/outlines_adapter.py
lexi_align/adapters/sglang_adapter.py
lexi_align/utils/__init__.py
lexi_align/utils/common.py
lexi_align-0.5.4.dist-info/METADATA
lexi_align-0.5.4.dist-info/WHEEL
lexi_align-0.5.4.dist-info/licenses/LICENSE
lexi_align-0.5.4.dist-info/RECORD
