Metadata-Version: 2.4
Name: lexi-align
Version: 0.5.4
Summary: Word alignment between two languages using structured generation
Author-email: Bor Hodošček <dev@bor.space>
License-File: LICENSE
Requires-Python: >=3.10
Requires-Dist: llm-schema-lite>=0.6.1
Requires-Dist: pydantic>=2.9.0
Requires-Dist: tqdm>=4.67.1
Provides-Extra: cpu
Requires-Dist: torch==2.8.0; extra == 'cpu'
Provides-Extra: cuda
Requires-Dist: bitsandbytes; extra == 'cuda'
Requires-Dist: flash-attn; extra == 'cuda'
Requires-Dist: torch==2.8.0; extra == 'cuda'
Provides-Extra: litellm
Requires-Dist: litellm>=1.51.0; extra == 'litellm'
Provides-Extra: llama-cpp
Requires-Dist: llama-cpp-python>=0.3.6; extra == 'llama-cpp'
Provides-Extra: outlines
Requires-Dist: accelerate>=1.0.1; extra == 'outlines'
Requires-Dist: datasets>=3.2.0; extra == 'outlines'
Requires-Dist: numba>=0.61.2; extra == 'outlines'
Requires-Dist: outlines>=1.2.8; extra == 'outlines'
Requires-Dist: protobuf>=5.29.1; extra == 'outlines'
Requires-Dist: sentencepiece>=0.2.0; extra == 'outlines'
Requires-Dist: transformers>=4.56.2; extra == 'outlines'
Provides-Extra: rocm
Requires-Dist: pytorch-triton-rocm==3.4.0; extra == 'rocm'
Requires-Dist: torch==2.8.0+rocm6.4; extra == 'rocm'
Provides-Extra: viz
Requires-Dist: altair>=5.5.0; extra == 'viz'
Requires-Dist: matplotlib>=3.9.2; extra == 'viz'
Requires-Dist: polars>=1.29.0; extra == 'viz'
Requires-Dist: pyfonts>=1.1.3; extra == 'viz'
Requires-Dist: seaborn>=0.13.2; extra == 'viz'
